aiogram_oop_framework/__init__.py
aiogram_oop_framework/__main__.py
aiogram_oop_framework/exceptions.py
aiogram_oop_framework/utils.py
aiogram_oop_framework/__pycache__/__init__.cpython-37.pyc
aiogram_oop_framework/__pycache__/exceptions.cpython-37.pyc
aiogram_oop_framework/__pycache__/utils.cpython-37.pyc
aiogram_oop_framework/core/__init__.py
aiogram_oop_framework/core/funcs.py
aiogram_oop_framework/core/project.py
aiogram_oop_framework/core/__pycache__/__init__.cpython-37.pyc
aiogram_oop_framework/core/__pycache__/funcs.cpython-37.pyc
aiogram_oop_framework/core/__pycache__/project.cpython-37.pyc
aiogram_oop_framework/core/management/__init__.py
aiogram_oop_framework/core/management/commands/__init__.py
aiogram_oop_framework/core/management/commands/startproject.py
aiogram_oop_framework/core/project_files_templates/__init__.py
aiogram_oop_framework/core/project_files_templates/__init__.txt
aiogram_oop_framework/core/project_files_templates/manage.txt
aiogram_oop_framework/core/project_files_templates/settings.txt
aiogram_oop_framework/core/project_files_templates/__pycache__/__init__.cpython-37.pyc
aiogram_oop_framework/filters/__init__.py
aiogram_oop_framework/filters/builtin.py
aiogram_oop_framework/filters/filters.py
aiogram_oop_framework/filters/__pycache__/__init__.cpython-37.pyc
aiogram_oop_framework/filters/__pycache__/builtin.cpython-37.pyc
aiogram_oop_framework/filters/__pycache__/filters.cpython-37.pyc
aiogram_oop_framework/views/__init__.py
aiogram_oop_framework/views/base.py
aiogram_oop_framework/views/callback_query.py
aiogram_oop_framework/views/channel_post_view.py
aiogram_oop_framework/views/chat_member.py
aiogram_oop_framework/views/chosen_inline_result.py
aiogram_oop_framework/views/edited_channel_post_view.py
aiogram_oop_framework/views/edited_message_view.py
aiogram_oop_framework/views/inline_query.py
aiogram_oop_framework/views/message.py
aiogram_oop_framework/views/my_chat_member.py
aiogram_oop_framework/views/poll.py
aiogram_oop_framework-0.9.5.dist-info/LICENSE
aiogram_oop_framework-0.9.5.dist-info/METADATA
aiogram_oop_framework-0.9.5.dist-info/WHEEL
aiogram_oop_framework-0.9.5.dist-info/top_level.txt
aiogram_oop_framework-0.9.5.dist-info/RECORD
