Metadata-Version: 2.1
Name: aiogram-oop-framework
Version: 0.9.5
Summary: An extender for aiogram to make it more OOP
Home-page: https://github.com/drforse/aiogram_oop_framework
Author: drforse
Author-email: george.lifeslice@gmail.com
License: UNKNOWN
Platform: UNKNOWN
Classifier: Programming Language :: Python :: 3
Classifier: License :: OSI Approved :: MIT License
Classifier: Operating System :: OS Independent
Requires-Python: >=3.7
License-File: LICENSE
Requires-Dist: aiogram (>=2.12)
Requires-Dist: click (==7.1.2)
